labbench_toolkit/__init__.py
labbench_toolkit/io.py
labbench_toolkit/psychophysics.py
labbench_toolkit/result.py
labbench_toolkit/protocols/stop_signal_task.py
labbench_toolkit/protocols/threshold_tracking.py
labbench_toolkit-0.0.4.dist-info/METADATA
labbench_toolkit-0.0.4.dist-info/WHEEL
labbench_toolkit-0.0.4.dist-info/licenses/LICENSE
labbench_toolkit-0.0.4.dist-info/RECORD
